{
  "Вовк": {
    "Удав": 0,
    "Лисиця": 0,
    "Ведмідь": 0,
    "Орел": 0,
    "Кінь": 10,
    "Олень": 15,
    "Кролик": 60,
    "Миша": 80,
    "Коза": 60,
    "Вівця": 70,
    "Кабан": 15,
    "Буйвол": 10,
    "Качка": 40,
    "Гусінь": 0,
    "Рослини": 0
  },
  "Удав": {
    "Вовк": 0,
    "Лисиця": 15,
    "Ведмідь": 0,
    "Орел": 0,
    "Кінь": 0,
    "Олень": 0,
    "Кролик": 20,
    "Миша": 40,
    "Коза": 0,
    "Вівця": 0,
    "Кабан": 0,
    "Буйвол": 0,
    "Качка": 10,
    "Гусінь": 0,
    "Рослини": 0
  },
  "Лисиця": {
    "Вовк": 0,
    "Удав": 0,
    "Ведмідь": 0,
    "Орел": 0,
    "Кінь": 0,
    "Олень": 0,
    "Кролик": 70,
    "Миша": 90,
    "Коза": 0,
    "Вівця": 0,
    "Кабан": 0,
    "Буйвол": 0,
    "Качка": 60,
    "Гусінь": 40,
    "Рослини": 0
  },
  "Ведмідь": {
    "Вовк": 0,
    "Удав": 80,
    "Лисиця": 0,
    "Орел": 0,
    "Кінь": 40,
    "Олень": 80,
    "Кролик": 80,
    "Миша": 90,
    "Коза": 70,
    "Вівця": 70,
    "Кабан": 50,
    "Буйвол": 20,
    "Качка": 10,
    "Гусінь": 0,
    "Рослини": 0
  },
  "Орел": {
    "Вовк": 0,
    "Удав": 0,
    "Лисиця": 10,
    "Ведмідь": 0,
    "Кінь": 0,
    "Олень": 0,
    "Кролик": 90,
    "Миша": 90,
    "Коза": 0,
    "Вівця": 0,
    "Кабан": 0,
    "Буйвол": 0,
    "Качка": 80,
    "Гусінь": 0,
    "Рослини": 0
  },
  "Кінь": {
    "Вовк": 0,
    "Удав": 0,
    "Лисиця": 0,
    "Ведмідь": 0,
    "Орел": 0,
    "Олень": 0,
    "Кролик": 0,
    "Миша": 0,
    "Коза": 0,
    "Вівця": 0,
    "Кабан": 0,
    "Буйвол": 0,
    "Качка": 0,
    "Гусінь": 0,
    "Рослини": 100
  },
  "Олень": {
    "Вовк": 0,
    "Удав": 0,
    "Лисиця": 0,
    "Ведмідь": 0,
    "Орел": 0,
    "Кінь": 0,
    "Кролик": 0,
    "Миша": 0,
    "Коза": 0,
    "Вівця": 0,
    "Кабан": 0,
    "Буйвол": 0,
    "Качка": 0,
    "Гусінь": 0,
    "Рослини": 100
  },
  "Кролик": {
    "Вовк": 0,
    "Удав": 0,
    "Лисиця": 0,
    "Ведмідь": 0,
    "Орел": 0,
    "Кінь": 0,
    "Олень": 0,
    "Миша": 0,
    "Коза": 0,
    "Вівця": 0,
    "Кабан": 0,
    "Буйвол": 0,
    "Качка": 0,
    "Гусінь": 0,
    "Рослини": 100
  },
  "Миша": {
    "Вовк": 0,
    "Удав": 0,
    "Лисиця": 0,
    "Ведмідь": 0,
    "Орел": 0,
    "Кінь": 0,
    "Олень": 0,
    "Кролик": 0,
    "Коза": 0,
    "Вівця": 0,
    "Кабан": 0,
    "Буйвол": 0,
    "Качка": 0,
    "Гусінь": 90,
    "Рослини": 100
  },
  "Коза": {
    "Вовк": 0,
    "Удав": 0,
    "Лисиця": 0,
    "Ведмідь": 0,
    "Орел": 0,
    "Кінь": 0,
    "Олень": 0,
    "Кролик": 0,
    "Миша": 0,
    "Вівця": 0,
    "Кабан": 0,
    "Буйвол": 0,
    "Качка": 0,
    "Гусінь": 0,
    "Рослини": 100
  },
  "Вівця": {
    "Вовк": 0,
    "Удав": 0,
    "Лисиця": 0,
    "Ведмідь": 0,
    "Орел": 0,
    "Кінь": 0,
    "Олень": 0,
    "Кролик": 0,
    "Миша": 0,
    "Коза": 0,
    "Кабан": 0,
    "Буйвол": 0,
    "Качка": 0,
    "Гусінь": 0,
    "Рослини": 100
  },
  "Кабан": {
    "Вовк": 0,
    "Удав": 0,
    "Лисиця": 0,
    "Ведмідь": 0,
    "Орел": 0,
    "Кінь": 0,
    "Олень": 0,
    "Кролик": 50,
    "Миша": 0,
    "Коза": 0,
    "Вівця": 0,
    "Буйвол": 0,
    "Качка": 0,
    "Гусінь": 90,
    "Рослини": 100
  },
  "Буйвол": {
    "Вовк": 0,
    "Удав": 0,
    "Лисиця": 0,
    "Ведмідь": 0,
    "Орел": 0,
    "Кінь": 0,
    "Олень": 0,
    "Кролик": 0,
    "Миша": 0,
    "Коза": 0,
    "Вівця": 0,
    "Кабан": 0,
    "Качка": 0,
    "Гусінь": 0,
    "Рослини": 100
  },
  "Качка": {
    "Вовк": 0,
    "Удав": 0,
    "Лисиця": 0,
    "Ведмідь": 0,
    "Орел": 0,
    "Кінь": 0,
    "Олень": 0,
    "Кролик": 0,
    "Миша": 0,
    "Коза": 0,
    "Вівця": 0,
    "Кабан": 0,
    "Буйвол": 0,
    "Гусінь": 90,
    "Рослини": 100
  },
  "Гусінь": {
    "Вовк": 0,
    "Удав": 0,
    "Лисиця": 0,
    "Ведмідь": 0,
    "Орел": 0,
    "Кінь": 0,
    "Олень": 0,
    "Кролик": 0,
    "Миша": 0,
    "Коза": 0,
    "Вівця": 0,
    "Кабан": 0,
    "Буйвол": 0,
    "Качка": 0,
    "Рослини": 100
  }
}